[
    {
        "end_col": 13,
        "end_file": "./src/t.rs",
        "end_line": 10,
        "name": "a",
        "start_col": 12,
        "start_file": "./src/t.rs",
        "start_line": 10,
        "ty": "i32"
    },
    {
        "end_col": 17,
        "end_file": "./src/t.rs",
        "end_line": 11,
        "name": "b",
        "start_col": 12,
        "start_file": "./src/t.rs",
        "start_line": 11,
        "ty": "bool"
    },
    {
        "end_col": 13,
        "end_file": "./src/t.rs",
        "end_line": 10,
        "name": "a",
        "start_col": 12,
        "start_file": "./src/t.rs",
        "start_line": 10,
        "ty": "i32"
    },
    {
        "end_col": 17,
        "end_file": "./src/t.rs",
        "end_line": 11,
        "name": "b",
        "start_col": 12,
        "start_file": "./src/t.rs",
        "start_line": 11,
        "ty": "bool"
    },
    {
        "end_col": 22,
        "end_file": "./src/t.rs",
        "end_line": 17,
        "name": "instance_b",
        "start_col": 8,
        "start_file": "./src/t.rs",
        "start_line": 17,
        "ty": "mod_a::StructB"
    },
    {
        "end_col": 14,
        "end_file": "./src/t.rs",
        "end_line": 18,
        "name": "instance_b",
        "start_col": 4,
        "start_file": "./src/t.rs",
        "start_line": 18,
        "ty": "mod_a::StructB"
    }
]